nonediag/__main__.py
nonediag/base.py
nonediag/deref.py
nonediag/models.py
nonediag/versions.py
nonediag-0.1.0.dist-info/LICENSE
nonediag-0.1.0.dist-info/METADATA
nonediag-0.1.0.dist-info/WHEEL
nonediag-0.1.0.dist-info/entry_points.txt
nonediag-0.1.0.dist-info/top_level.txt
nonediag-0.1.0.dist-info/RECORD
